simulator/__init__.py
simulator/cli.py
simulator/configuration.py
simulator/image_creation.py
simulator/pictures_generation.py
simulator/povray.pov
simulator/utils.py
simulator/profil_generation_template/configuration.json
simulator/profil_generation_template/grounds/IMG_1417.jpg
simulator/profil_generation_template/grounds/IMG_5993.jpg
simulator/profil_generation_template/photos/.gitkeep
tests/__init__.py
tests/acceptances/__init__.py
tests/acceptances/test_cli.py
tests/acceptances/test_pictures_generation.py
tests/acceptances/test_profil_generation_template.py
tests/acceptances/fixtures/__init__.py
simulateur_ironcar-1.0.6.post1.dist-info/LICENSE
simulateur_ironcar-1.0.6.post1.dist-info/METADATA
simulateur_ironcar-1.0.6.post1.dist-info/WHEEL
simulateur_ironcar-1.0.6.post1.dist-info/entry_points.txt
simulateur_ironcar-1.0.6.post1.dist-info/top_level.txt
simulateur_ironcar-1.0.6.post1.dist-info/RECORD
