Metadata-Version: 2.1
Name: simulateur-ironcar
Version: 1.0.6.post1
Summary: UNKNOWN
Home-page: UNKNOWN
License: MIT license
Platform: UNKNOWN
Classifier: Programming Language :: Python :: 3.5
Classifier: Programming Language :: Python :: 3.6
Classifier: License :: OSI Approved :: MIT License
Classifier: Environment :: Console
Requires-Dist: numpy
Requires-Dist: matplotlib
Requires-Dist: opencv-python
Requires-Dist: Pillow
Requires-Dist: click
Requires-Dist: decorator
Provides-Extra: dev
Requires-Dist: pytest ; extra == 'dev'
Requires-Dist: pylint ; extra == 'dev'
Requires-Dist: jupyter ; extra == 'dev'
Requires-Dist: twine ; extra == 'dev'
